jdclip/__init__.py
jdclip-0.0.2.dist-info/METADATA
jdclip-0.0.2.dist-info/WHEEL
jdclip-0.0.2.dist-info/dependency_links.txt
jdclip-0.0.2.dist-info/top_level.txt
jdclip-0.0.2.dist-info/RECORD
